<?xml version="1.0" encoding="UTF-8" standalone="no"?>
<ODDR>
    <version>
	<ver>1.9</ver>
	<last_updated>2012-08-03 09:31:00</last_updated>
        <official_url>openddr.org</official_url>
        <maintainers>
        </maintainers>
        <authors>
        </authors>
        <statement>
        <![CDATA[
        Copyright 2011 OpenDDR LLC
        This file is made available under the terms of the Open Database License: http://opendatacommons.org/licenses/odbl/1.0/.
        Any rights in individual contents of the database are licensed under the Database Contents License: http://opendatacommons.org/licenses/dbcl/1.0/
        ]]>
        </statement>
    </version>
    <!-- ODDR Vocabulary description -->
    <VocabularyDescription target="http://www.openddr.org/oddr-vocabulary">
	<!-- Aspects -->
        <Aspects>
            <Aspect name="device"/>
            <Aspect name="webBrowser"/>
            <Aspect name="operativeSystem"/>
<!--            <Aspect name="group"/>-->
        </Aspects>
<!--        <Variables>
            <Variable id="a" vocabulary="http://www.openddr.org/oddr-vocabulary" name="model" aspect="device" />
            <Variable id="b" vocabulary="http://www.openddr.org/oddr-vocabulary" name="vendor" aspect="device" />
            <Variable id="c" vocabulary="http://www.openddr.org/oddr-vocabulary" name="model" aspect="webBrowser" />
            <Variable id="d" vocabulary="http://www.openddr.org/oddr-vocabulary" name="notApple" aspect="group" />
        </Variables>-->
	<!-- Properties -->
        <Properties>
		<!-- Core Property -->
<!--            <Property name="notApple" datatype="xs:string" aspects="group" defaultAspect="group" expr="$a != 'iPhone'"/>
            <Property name="isApple" datatype="xs:string" aspects="group" defaultAspect="group" expr="($a == 'iPhone' || $a == 'iPad' || $a == 'iPod touch') and $d == 'true'"/>
            <Property name="isApple" datatype="xs:string" aspects="group" defaultAspect="group" expr="$a == 'iPhone' || $a == 'iPad' || $a == 'iPod touch'"/>
            <Property name="webkitUiSupport" datatype="xs:string" aspects="group" defaultAspect="group" expr="$b == 'Apple' || $c == 'Android Browser'"/>-->
            <Property name="id" datatype="xs:string" aspects="device" defaultAspect="device"/>
            <Property name="vendor" datatype="xs:string" aspects="device, webBrowser, operativeSystem" defaultAspect="device"/>
            <Property name="model" datatype="xs:string" aspects="device, webBrowser,  operativeSystem" defaultAspect="device"/>
            <Property name="displayWidth" datatype="xs:nonNegativeInteger" aspects="device, webBrowser" defaultAspect="device"/>
            <Property name="displayHeight" datatype="xs:nonNegativeInteger" aspects="device, webBrowser" defaultAspect="device"/>
            <Property name="displayColorDepth" datatype="xs:nonNegativeInteger" aspects="device" defaultAspect="device"/>
            <Property name="version" datatype="xs:string" aspects="device, webBrowser, operativeSystem" defaultAspect="device"/>
            <Property name="inputDevices" datatype="xs:enumeration" aspects="device" defaultAspect="device"/>
            <Property name="cookieSupport" datatype="xs:boolean" aspects="webBrowser" defaultAspect="webBrowser"/>
            <Property name="imageFormatSupport" datatype="xs:enumeration" aspects="webBrowser" defaultAspect="webBrowser"/>
            <Property name="inputModeSupport" datatype="xs:enumeration" aspects="webBrowser" defaultAspect="webBrowser"/>
            <Property name="stylesheetSupport" datatype="xs:enumeration" aspects="webBrowser" defaultAspect="webBrowser"/>
            <Property name="markupSupport" datatype="xs:enumeration" aspects="webBrowser" defaultAspect="webBrowser"/>
            <Property name="scriptSupport" datatype="xs:enumeration" aspects="webBrowser" defaultAspect="webBrowser"/>
		<!-- ODDR property -->	
            <Property aspects="device" datatype="xs:string" defaultAspect="device" name="mobile_browser"/>
            <Property aspects="device" datatype="xs:integer" defaultAspect="device" name="nokia_feature_pack"/>
            <Property aspects="device" datatype="xs:string" defaultAspect="device" name="device_os"/>
            <Property aspects="device" datatype="xs:integer" defaultAspect="device" name="nokia_series"/>
            <Property aspects="device" datatype="xs:boolean" defaultAspect="device" name="has_qwerty_keyboard"/>
            <Property aspects="device" datatype="xs:string" defaultAspect="device" name="mobile_browser_version"/>
            <Property aspects="device" datatype="xs:boolean" defaultAspect="device" name="is_tablet"/>
            <Property aspects="device" datatype="xs:integer" defaultAspect="device" name="nokia_edition"/>
            <Property aspects="device" datatype="xs:string" defaultAspect="device" name="uaprof"/>
            <Property aspects="device" datatype="xs:boolean" defaultAspect="device" name="can_skip_aligned_link_row"/>
            <Property aspects="device" datatype="xs:boolean" defaultAspect="device" name="device_claims_web_support"/>
            <Property aspects="device" datatype="xs:string" defaultAspect="device" name="ununiqueness_handler"/>
            <Property aspects="device" datatype="xs:string" defaultAspect="device" name="device_os_version"/>
            <Property aspects="device" datatype="xs:string" defaultAspect="device" name="uaprof2"/>
            <Property aspects="device" datatype="xs:boolean" defaultAspect="device" name="is_wireless_device"/>
            <Property aspects="device" datatype="xs:string" defaultAspect="device" name="uaprof3"/>
            <Property aspects="device" datatype="xs:string" defaultAspect="device" name="model_extra_info"/>
            <Property aspects="device" datatype="xs:string" defaultAspect="device" name="marketing_name"/>
            <Property aspects="device" datatype="xs:boolean" defaultAspect="device" name="can_assign_phone_number"/>
            <Property aspects="device" datatype="xs:string" defaultAspect="device" name="release_date"/>
            <Property aspects="device" datatype="xs:boolean" defaultAspect="device" name="unique"/>
            <Property aspects="device" datatype="xs:boolean" defaultAspect="device" name="icons_on_menu_items_support"/>
            <Property aspects="device" datatype="xs:boolean" defaultAspect="device" name="opwv_wml_extensions_support"/>
            <Property aspects="device" datatype="xs:boolean" defaultAspect="device" name="built_in_back_button_support"/>
            <Property aspects="device" datatype="xs:boolean" defaultAspect="device" name="proportional_font"/>
            <Property aspects="device" datatype="xs:boolean" defaultAspect="device" name="insert_br_element_after_widget_recommended"/>
            <Property aspects="device" datatype="xs:boolean" defaultAspect="device" name="wizards_recommended"/>
            <Property aspects="device" datatype="xs:boolean" defaultAspect="device" name="wml_can_display_images_and_text_on_same_line"/>
            <Property aspects="device" datatype="xs:boolean" defaultAspect="device" name="softkey_support"/>
            <Property aspects="device" datatype="xs:string" defaultAspect="device" name="wml_make_phone_call_string"/>
            <Property aspects="device" datatype="xs:boolean" defaultAspect="device" name="deck_prefetch_support"/>
            <Property aspects="device" datatype="xs:boolean" defaultAspect="device" name="menu_with_select_element_recommended"/>
            <Property aspects="device" datatype="xs:boolean" defaultAspect="device" name="numbered_menus"/>
            <Property aspects="device" datatype="xs:boolean" defaultAspect="device" name="card_title_support"/>
            <Property aspects="device" datatype="xs:boolean" defaultAspect="device" name="image_as_link_support"/>
            <Property aspects="device" datatype="xs:boolean" defaultAspect="device" name="wrap_mode_support"/>
            <Property aspects="device" datatype="xs:boolean" defaultAspect="device" name="table_support"/>
            <Property aspects="device" datatype="xs:boolean" defaultAspect="device" name="access_key_support"/>
            <Property aspects="device" datatype="xs:boolean" defaultAspect="device" name="wml_displays_image_in_center"/>
            <Property aspects="device" datatype="xs:boolean" defaultAspect="device" name="elective_forms_recommended"/>
            <Property aspects="device" datatype="xs:boolean" defaultAspect="device" name="times_square_mode_support"/>
            <Property aspects="device" datatype="xs:boolean" defaultAspect="device" name="break_list_of_links_with_br_element_recommended"/>
            <Property aspects="device" datatype="xs:boolean" defaultAspect="device" name="menu_with_list_of_links_recommended"/>
            <Property aspects="device" datatype="xs:string" defaultAspect="device" name="imode_region"/>
            <Property aspects="device" datatype="xs:boolean" defaultAspect="device" name="chtml_can_display_images_and_text_on_same_line"/>
            <Property aspects="device" datatype="xs:boolean" defaultAspect="device" name="chtml_displays_image_in_center"/>
            <Property aspects="device" datatype="xs:string" defaultAspect="device" name="chtml_make_phone_call_string"/>
            <Property aspects="device" datatype="xs:boolean" defaultAspect="device" name="chtml_table_support"/>
            <Property aspects="device" datatype="xs:boolean" defaultAspect="device" name="chtml_display_accesskey"/>
            <Property aspects="device" datatype="xs:boolean" defaultAspect="device" name="emoji"/>
            <Property aspects="device" datatype="xs:string" defaultAspect="device" name="xhtml_preferred_charset"/>
            <Property aspects="device" datatype="xs:boolean" defaultAspect="device" name="xhtml_supports_css_cell_table_coloring"/>
            <Property aspects="device" datatype="xs:boolean" defaultAspect="device" name="xhtml_select_as_radiobutton"/>
            <Property aspects="device" datatype="xs:boolean" defaultAspect="device" name="xhtml_autoexpand_select"/>
            <Property aspects="device" datatype="xs:boolean" defaultAspect="device" name="xhtml_avoid_accesskeys"/>
            <Property aspects="device" datatype="xs:boolean" defaultAspect="device" name="accept_third_party_cookie"/>
            <Property aspects="device" datatype="xs:string" defaultAspect="device" name="xhtml_make_phone_call_string"/>
            <Property aspects="device" datatype="xs:boolean" defaultAspect="device" name="xhtml_allows_disabled_form_elements"/>
            <Property aspects="device" datatype="xs:boolean" defaultAspect="device" name="xhtml_supports_invisible_text"/>
            <Property aspects="device" datatype="xs:boolean" defaultAspect="device" name="xhtml_select_as_dropdown"/>
            <Property aspects="device" datatype="xs:string" defaultAspect="device" name="xhtml_send_mms_string"/>
            <Property aspects="device" datatype="xs:boolean" defaultAspect="device" name="xhtml_table_support"/>
            <Property aspects="device" datatype="xs:boolean" defaultAspect="device" name="xhtml_display_accesskey"/>
            <Property aspects="device" datatype="xs:string" defaultAspect="device" name="xhtml_can_embed_video"/>
            <Property aspects="device" datatype="xs:string" defaultAspect="device" name="xhtml_supports_iframe"/>
            <Property aspects="device" datatype="xs:string" defaultAspect="device" name="xhtmlmp_preferred_mime_type"/>
            <Property aspects="device" datatype="xs:boolean" defaultAspect="device" name="xhtml_supports_monospace_font"/>
            <Property aspects="device" datatype="xs:boolean" defaultAspect="device" name="xhtml_supports_inline_input"/>
            <Property aspects="device" datatype="xs:boolean" defaultAspect="device" name="xhtml_supports_forms_in_table"/>
            <Property aspects="device" datatype="xs:boolean" defaultAspect="device" name="xhtml_document_title_support"/>
            <Property aspects="device" datatype="xs:boolean" defaultAspect="device" name="xhtml_support_wml2_namespace"/>
            <Property aspects="device" datatype="xs:string" defaultAspect="device" name="xhtml_readable_background_color1"/>
            <Property aspects="device" datatype="xs:boolean" defaultAspect="device" name="xhtml_format_as_attribute"/>
            <Property aspects="device" datatype="xs:boolean" defaultAspect="device" name="xhtml_supports_table_for_layout"/>
            <Property aspects="device" datatype="xs:string" defaultAspect="device" name="xhtml_readable_background_color2"/>
            <Property aspects="device" datatype="xs:boolean" defaultAspect="device" name="xhtml_select_as_popup"/>
            <Property aspects="device" datatype="xs:string" defaultAspect="device" name="xhtml_send_sms_string"/>
            <Property aspects="device" datatype="xs:boolean" defaultAspect="device" name="xhtml_format_as_css_property"/>
            <Property aspects="device" datatype="xs:string" defaultAspect="device" name="xhtml_file_upload"/>
            <Property aspects="device" datatype="xs:boolean" defaultAspect="device" name="xhtml_honors_bgcolor"/>
            <Property aspects="device" datatype="xs:boolean" defaultAspect="device" name="opwv_xhtml_extensions_support"/>
            <Property aspects="device" datatype="xs:boolean" defaultAspect="device" name="xhtml_marquee_as_css_property"/>
            <Property aspects="device" datatype="xs:boolean" defaultAspect="device" name="xhtml_nowrap_mode"/>
            <Property aspects="device" datatype="xs:string" defaultAspect="device" name="ajax_preferred_geoloc_api"/>
            <Property aspects="device" datatype="xs:string" defaultAspect="device" name="ajax_xhr_type"/>
            <Property aspects="device" datatype="xs:boolean" defaultAspect="device" name="ajax_support_getelementbyid"/>
            <Property aspects="device" datatype="xs:boolean" defaultAspect="device" name="ajax_support_event_listener"/>
            <Property aspects="device" datatype="xs:boolean" defaultAspect="device" name="ajax_manipulate_dom"/>
            <Property aspects="device" datatype="xs:boolean" defaultAspect="device" name="ajax_support_javascript"/>
            <Property aspects="device" datatype="xs:boolean" defaultAspect="device" name="ajax_support_inner_html"/>
            <Property aspects="device" datatype="xs:boolean" defaultAspect="device" name="ajax_manipulate_css"/>
            <Property aspects="device" datatype="xs:boolean" defaultAspect="device" name="ajax_support_events"/>
            <Property aspects="device" datatype="xs:boolean" defaultAspect="device" name="html_web_3_2"/>
            <Property aspects="device" datatype="xs:boolean" defaultAspect="device" name="html_wi_imode_htmlx_1"/>
            <Property aspects="device" datatype="xs:boolean" defaultAspect="device" name="html_wi_imode_html_1"/>
            <Property aspects="device" datatype="xs:boolean" defaultAspect="device" name="html_wi_oma_xhtmlmp_1_0"/>
            <Property aspects="device" datatype="xs:boolean" defaultAspect="device" name="html_wi_imode_html_2"/>
            <Property aspects="device" datatype="xs:boolean" defaultAspect="device" name="html_wi_w3_xhtmlbasic"/>
            <Property aspects="device" datatype="xs:boolean" defaultAspect="device" name="html_wi_imode_compact_generic"/>
            <Property aspects="device" datatype="xs:boolean" defaultAspect="device" name="html_wi_imode_html_3"/>
            <Property aspects="device" datatype="xs:boolean" defaultAspect="device" name="wml_1_1"/>
            <Property aspects="device" datatype="xs:boolean" defaultAspect="device" name="html_wi_imode_html_4"/>
            <Property aspects="device" datatype="xs:boolean" defaultAspect="device" name="wml_1_2"/>
            <Property aspects="device" datatype="xs:boolean" defaultAspect="device" name="html_wi_imode_html_5"/>
            <Property aspects="device" datatype="xs:boolean" defaultAspect="device" name="wml_1_3"/>
            <Property aspects="device" datatype="xs:string" defaultAspect="device" name="preferred_markup"/>
            <Property aspects="device" datatype="xs:integer" defaultAspect="device" name="xhtml_support_level"/>
            <Property aspects="device" datatype="xs:boolean" defaultAspect="device" name="voicexml"/>
            <Property aspects="device" datatype="xs:boolean" defaultAspect="device" name="html_wi_imode_htmlx_1_1"/>
            <Property aspects="device" datatype="xs:boolean" defaultAspect="device" name="multipart_support"/>
            <Property aspects="device" datatype="xs:boolean" defaultAspect="device" name="html_web_4_0"/>
            <Property aspects="device" datatype="xs:boolean" defaultAspect="device" name="time_to_live_support"/>
            <Property aspects="device" datatype="xs:boolean" defaultAspect="device" name="total_cache_disable_support"/>
            <Property aspects="device" datatype="xs:string" defaultAspect="device" name="physical_screen_height"/>
            <Property aspects="device" datatype="xs:string" defaultAspect="device" name="columns"/>
            <Property aspects="device" datatype="xs:boolean" defaultAspect="device" name="dual_orientation"/>
            <Property aspects="device" datatype="xs:string" defaultAspect="device" name="physical_screen_width"/>
            <Property aspects="device" datatype="xs:integer" defaultAspect="device" name="rows"/>
            <Property aspects="device" datatype="xs:string" defaultAspect="device" name="max_image_width"/>
            <Property aspects="device" datatype="xs:string" defaultAspect="device" name="max_image_height"/>
            <Property aspects="device" datatype="xs:boolean" defaultAspect="device" name="greyscale"/>
            <Property aspects="device" datatype="xs:boolean" defaultAspect="device" name="jpg"/>
            <Property aspects="device" datatype="xs:boolean" defaultAspect="device" name="gif"/>
            <Property aspects="device" datatype="xs:boolean" defaultAspect="device" name="transparent_png_index"/>
            <Property aspects="device" datatype="xs:boolean" defaultAspect="device" name="epoc_bmp"/>
            <Property aspects="device" datatype="xs:boolean" defaultAspect="device" name="bmp"/>
            <Property aspects="device" datatype="xs:boolean" defaultAspect="device" name="wbmp"/>
            <Property aspects="device" datatype="xs:boolean" defaultAspect="device" name="gif_animated"/>
            <Property aspects="device" datatype="xs:boolean" defaultAspect="device" name="svgt_1_1_plus"/>
            <Property aspects="device" datatype="xs:boolean" defaultAspect="device" name="svgt_1_1"/>
            <Property aspects="device" datatype="xs:boolean" defaultAspect="device" name="transparent_png_alpha"/>
            <Property aspects="device" datatype="xs:boolean" defaultAspect="device" name="png"/>
            <Property aspects="device" datatype="xs:boolean" defaultAspect="device" name="tiff"/>
            <Property aspects="device" datatype="xs:boolean" defaultAspect="device" name="emptyok"/>
            <Property aspects="device" datatype="xs:boolean" defaultAspect="device" name="empty_option_value_support"/>
            <Property aspects="device" datatype="xs:boolean" defaultAspect="device" name="basic_authentication_support"/>
            <Property aspects="device" datatype="xs:boolean" defaultAspect="device" name="post_method_support"/>
            <Property aspects="device" datatype="xs:boolean" defaultAspect="device" name="nokia_voice_call"/>
            <Property aspects="device" datatype="xs:boolean" defaultAspect="device" name="wta_pdc"/>
            <Property aspects="device" datatype="xs:boolean" defaultAspect="device" name="wta_voice_call"/>
            <Property aspects="device" datatype="xs:boolean" defaultAspect="device" name="wta_misc"/>
            <Property aspects="device" datatype="xs:boolean" defaultAspect="device" name="wta_phonebook"/>
            <Property aspects="device" datatype="xs:boolean" defaultAspect="device" name="phone_id_provided"/>
            <Property aspects="device" datatype="xs:boolean" defaultAspect="device" name="https_support"/>
            <Property aspects="device" datatype="xs:boolean" defaultAspect="device" name="sdio"/>
            <Property aspects="device" datatype="xs:boolean" defaultAspect="device" name="wifi"/>
            <Property aspects="device" datatype="xs:boolean" defaultAspect="device" name="has_cellular_radio"/>
            <Property aspects="device" datatype="xs:integer" defaultAspect="device" name="max_data_rate"/>
            <Property aspects="device" datatype="xs:boolean" defaultAspect="device" name="vpn"/>
            <Property aspects="device" datatype="xs:integer" defaultAspect="device" name="max_length_of_username"/>
            <Property aspects="device" datatype="xs:integer" defaultAspect="device" name="max_url_length_bookmark"/>
            <Property aspects="device" datatype="xs:integer" defaultAspect="device" name="max_no_of_bookmarks"/>
            <Property aspects="device" datatype="xs:string" defaultAspect="device" name="max_deck_size"/>
            <Property aspects="device" datatype="xs:integer" defaultAspect="device" name="max_url_length_cached_page"/>
            <Property aspects="device" datatype="xs:integer" defaultAspect="device" name="max_length_of_password"/>
            <Property aspects="device" datatype="xs:integer" defaultAspect="device" name="max_no_of_connection_settings"/>
            <Property aspects="device" datatype="xs:string" defaultAspect="device" name="max_url_length_in_requests"/>
            <Property aspects="device" datatype="xs:integer" defaultAspect="device" name="max_object_size"/>
            <Property aspects="device" datatype="xs:integer" defaultAspect="device" name="max_url_length_homepage"/>
            <Property aspects="device" datatype="xs:boolean" defaultAspect="device" name="video"/>
            <Property aspects="device" datatype="xs:boolean" defaultAspect="device" name="picture_bmp"/>
            <Property aspects="device" datatype="xs:boolean" defaultAspect="device" name="picture"/>
            <Property aspects="device" datatype="xs:integer" defaultAspect="device" name="wallpaper_df_size_limit"/>
            <Property aspects="device" datatype="xs:integer" defaultAspect="device" name="picture_preferred_width"/>
            <Property aspects="device" datatype="xs:integer" defaultAspect="device" name="wallpaper_oma_size_limit"/>
            <Property aspects="device" datatype="xs:boolean" defaultAspect="device" name="picture_greyscale"/>
            <Property aspects="device" datatype="xs:boolean" defaultAspect="device" name="inline_support"/>
            <Property aspects="device" datatype="xs:boolean" defaultAspect="device" name="ringtone_qcelp"/>
            <Property aspects="device" datatype="xs:integer" defaultAspect="device" name="screensaver_oma_size_limit"/>
            <Property aspects="device" datatype="xs:boolean" defaultAspect="device" name="screensaver_wbmp"/>
            <Property aspects="device" datatype="xs:string" defaultAspect="device" name="picture_resize"/>
            <Property aspects="device" datatype="xs:integer" defaultAspect="device" name="picture_preferred_height"/>
            <Property aspects="device" datatype="xs:boolean" defaultAspect="device" name="ringtone_rmf"/>
            <Property aspects="device" datatype="xs:boolean" defaultAspect="device" name="wallpaper_wbmp"/>
            <Property aspects="device" datatype="xs:boolean" defaultAspect="device" name="wallpaper_jpg"/>
            <Property aspects="device" datatype="xs:boolean" defaultAspect="device" name="screensaver_bmp"/>
            <Property aspects="device" datatype="xs:integer" defaultAspect="device" name="screensaver_max_width"/>
            <Property aspects="device" datatype="xs:integer" defaultAspect="device" name="picture_inline_size_limit"/>
            <Property aspects="device" datatype="xs:integer" defaultAspect="device" name="picture_colors"/>
            <Property aspects="device" datatype="xs:boolean" defaultAspect="device" name="ringtone_midi_polyphonic"/>
            <Property aspects="device" datatype="xs:boolean" defaultAspect="device" name="ringtone_midi_monophonic"/>
            <Property aspects="device" datatype="xs:integer" defaultAspect="device" name="screensaver_preferred_height"/>
            <Property aspects="device" datatype="xs:integer" defaultAspect="device" name="ringtone_voices"/>
            <Property aspects="device" datatype="xs:boolean" defaultAspect="device" name="ringtone_3gpp"/>
            <Property aspects="device" datatype="xs:boolean" defaultAspect="device" name="oma_support"/>
            <Property aspects="device" datatype="xs:integer" defaultAspect="device" name="ringtone_inline_size_limit"/>
            <Property aspects="device" datatype="xs:integer" defaultAspect="device" name="wallpaper_preferred_width"/>
            <Property aspects="device" datatype="xs:boolean" defaultAspect="device" name="wallpaper_greyscale"/>
            <Property aspects="device" datatype="xs:integer" defaultAspect="device" name="screensaver_preferred_width"/>
            <Property aspects="device" datatype="xs:integer" defaultAspect="device" name="wallpaper_preferred_height"/>
            <Property aspects="device" datatype="xs:integer" defaultAspect="device" name="picture_max_width"/>
            <Property aspects="device" datatype="xs:boolean" defaultAspect="device" name="picture_jpg"/>
            <Property aspects="device" datatype="xs:boolean" defaultAspect="device" name="ringtone_aac"/>
            <Property aspects="device" datatype="xs:integer" defaultAspect="device" name="ringtone_oma_size_limit"/>
            <Property aspects="device" datatype="xs:integer" defaultAspect="device" name="wallpaper_directdownload_size_limit"/>
            <Property aspects="device" datatype="xs:integer" defaultAspect="device" name="screensaver_inline_size_limit"/>
            <Property aspects="device" datatype="xs:boolean" defaultAspect="device" name="ringtone_xmf"/>
            <Property aspects="device" datatype="xs:integer" defaultAspect="device" name="picture_max_height"/>
            <Property aspects="device" datatype="xs:integer" defaultAspect="device" name="screensaver_max_height"/>
            <Property aspects="device" datatype="xs:boolean" defaultAspect="device" name="ringtone_mp3"/>
            <Property aspects="device" datatype="xs:boolean" defaultAspect="device" name="wallpaper_png"/>
            <Property aspects="device" datatype="xs:boolean" defaultAspect="device" name="screensaver_jpg"/>
            <Property aspects="device" datatype="xs:integer" defaultAspect="device" name="ringtone_directdownload_size_limit"/>
            <Property aspects="device" datatype="xs:integer" defaultAspect="device" name="wallpaper_max_width"/>
            <Property aspects="device" datatype="xs:integer" defaultAspect="device" name="wallpaper_max_height"/>
            <Property aspects="device" datatype="xs:boolean" defaultAspect="device" name="screensaver"/>
            <Property aspects="device" datatype="xs:boolean" defaultAspect="device" name="ringtone_wav"/>
            <Property aspects="device" datatype="xs:boolean" defaultAspect="device" name="wallpaper_gif"/>
            <Property aspects="device" datatype="xs:integer" defaultAspect="device" name="screensaver_directdownload_size_limit"/>
            <Property aspects="device" datatype="xs:integer" defaultAspect="device" name="picture_df_size_limit"/>
            <Property aspects="device" datatype="xs:boolean" defaultAspect="device" name="wallpaper_tiff"/>
            <Property aspects="device" datatype="xs:integer" defaultAspect="device" name="screensaver_df_size_limit"/>
            <Property aspects="device" datatype="xs:boolean" defaultAspect="device" name="ringtone_awb"/>
            <Property aspects="device" datatype="xs:boolean" defaultAspect="device" name="ringtone"/>
            <Property aspects="device" datatype="xs:integer" defaultAspect="device" name="wallpaper_inline_size_limit"/>
            <Property aspects="device" datatype="xs:integer" defaultAspect="device" name="picture_directdownload_size_limit"/>
            <Property aspects="device" datatype="xs:boolean" defaultAspect="device" name="picture_png"/>
            <Property aspects="device" datatype="xs:boolean" defaultAspect="device" name="wallpaper_bmp"/>
            <Property aspects="device" datatype="xs:boolean" defaultAspect="device" name="picture_wbmp"/>
            <Property aspects="device" datatype="xs:integer" defaultAspect="device" name="ringtone_df_size_limit"/>
            <Property aspects="device" datatype="xs:integer" defaultAspect="device" name="picture_oma_size_limit"/>
            <Property aspects="device" datatype="xs:boolean" defaultAspect="device" name="picture_gif"/>
            <Property aspects="device" datatype="xs:boolean" defaultAspect="device" name="screensaver_png"/>
            <Property aspects="device" datatype="xs:string" defaultAspect="device" name="wallpaper_resize"/>
            <Property aspects="device" datatype="xs:boolean" defaultAspect="device" name="screensaver_greyscale"/>
            <Property aspects="device" datatype="xs:boolean" defaultAspect="device" name="ringtone_mmf"/>
            <Property aspects="device" datatype="xs:boolean" defaultAspect="device" name="ringtone_amr"/>
            <Property aspects="device" datatype="xs:boolean" defaultAspect="device" name="wallpaper"/>
            <Property aspects="device" datatype="xs:boolean" defaultAspect="device" name="ringtone_digiplug"/>
            <Property aspects="device" datatype="xs:boolean" defaultAspect="device" name="ringtone_spmidi"/>
            <Property aspects="device" datatype="xs:boolean" defaultAspect="device" name="ringtone_compactmidi"/>
            <Property aspects="device" datatype="xs:boolean" defaultAspect="device" name="ringtone_imelody"/>
            <Property aspects="device" datatype="xs:string" defaultAspect="device" name="screensaver_resize"/>
            <Property aspects="device" datatype="xs:integer" defaultAspect="device" name="wallpaper_colors"/>
            <Property aspects="device" datatype="xs:boolean" defaultAspect="device" name="directdownload_support"/>
            <Property aspects="device" datatype="xs:boolean" defaultAspect="device" name="downloadfun_support"/>
            <Property aspects="device" datatype="xs:integer" defaultAspect="device" name="screensaver_colors"/>
            <Property aspects="device" datatype="xs:boolean" defaultAspect="device" name="screensaver_gif"/>
            <Property aspects="device" datatype="xs:boolean" defaultAspect="device" name="oma_v_1_0_combined_delivery"/>
            <Property aspects="device" datatype="xs:boolean" defaultAspect="device" name="oma_v_1_0_separate_delivery"/>
            <Property aspects="device" datatype="xs:boolean" defaultAspect="device" name="oma_v_1_0_forwardlock"/>
            <Property aspects="device" datatype="xs:string" defaultAspect="device" name="streaming_vcodec_mpeg4_asp"/>
            <Property aspects="device" datatype="xs:integer" defaultAspect="device" name="streaming_video_size_limit"/>
            <Property aspects="device" datatype="xs:boolean" defaultAspect="device" name="streaming_mov"/>
            <Property aspects="device" datatype="xs:string" defaultAspect="device" name="streaming_wmv"/>
            <Property aspects="device" datatype="xs:string" defaultAspect="device" name="streaming_acodec_aac"/>
            <Property aspects="device" datatype="xs:string" defaultAspect="device" name="streaming_vcodec_h263_0"/>
            <Property aspects="device" datatype="xs:string" defaultAspect="device" name="streaming_real_media"/>
            <Property aspects="device" datatype="xs:boolean" defaultAspect="device" name="streaming_3g2"/>
            <Property aspects="device" datatype="xs:boolean" defaultAspect="device" name="streaming_3gpp"/>
            <Property aspects="device" datatype="xs:string" defaultAspect="device" name="streaming_acodec_amr"/>
            <Property aspects="device" datatype="xs:string" defaultAspect="device" name="streaming_vcodec_h264_bp"/>
            <Property aspects="device" datatype="xs:string" defaultAspect="device" name="streaming_vcodec_h263_3"/>
            <Property aspects="device" datatype="xs:string" defaultAspect="device" name="streaming_preferred_protocol"/>
            <Property aspects="device" datatype="xs:string" defaultAspect="device" name="streaming_vcodec_mpeg4_sp"/>
            <Property aspects="device" datatype="xs:boolean" defaultAspect="device" name="streaming_flv"/>
            <Property aspects="device" datatype="xs:boolean" defaultAspect="device" name="streaming_video"/>
            <Property aspects="device" datatype="xs:boolean" defaultAspect="device" name="streaming_mp4"/>
            <Property aspects="device" datatype="xs:boolean" defaultAspect="device" name="expiration_date"/>
            <Property aspects="device" datatype="xs:boolean" defaultAspect="device" name="utf8_support"/>
            <Property aspects="device" datatype="xs:boolean" defaultAspect="device" name="connectionless_cache_operation"/>
            <Property aspects="device" datatype="xs:boolean" defaultAspect="device" name="connectionless_service_load"/>
            <Property aspects="device" datatype="xs:boolean" defaultAspect="device" name="iso8859_support"/>
            <Property aspects="device" datatype="xs:boolean" defaultAspect="device" name="connectionoriented_confirmed_service_indication"/>
            <Property aspects="device" datatype="xs:boolean" defaultAspect="device" name="connectionless_service_indication"/>
            <Property aspects="device" datatype="xs:boolean" defaultAspect="device" name="ascii_support"/>
            <Property aspects="device" datatype="xs:boolean" defaultAspect="device" name="connectionoriented_confirmed_cache_operation"/>
            <Property aspects="device" datatype="xs:boolean" defaultAspect="device" name="connectionoriented_confirmed_service_load"/>
            <Property aspects="device" datatype="xs:boolean" defaultAspect="device" name="wap_push_support"/>
            <Property aspects="device" datatype="xs:boolean" defaultAspect="device" name="connectionoriented_unconfirmed_cache_operation"/>
            <Property aspects="device" datatype="xs:boolean" defaultAspect="device" name="connectionoriented_unconfirmed_service_load"/>
            <Property aspects="device" datatype="xs:boolean" defaultAspect="device" name="connectionoriented_unconfirmed_service_indication"/>
            <Property aspects="device" datatype="xs:boolean" defaultAspect="device" name="doja_1_5"/>
            <Property aspects="device" datatype="xs:boolean" defaultAspect="device" name="j2me_datefield_broken"/>
            <Property aspects="device" datatype="xs:integer" defaultAspect="device" name="j2me_clear_key_code"/>
            <Property aspects="device" datatype="xs:integer" defaultAspect="device" name="j2me_right_softkey_code"/>
            <Property aspects="device" datatype="xs:integer" defaultAspect="device" name="j2me_heap_size"/>
            <Property aspects="device" datatype="xs:integer" defaultAspect="device" name="j2me_canvas_width"/>
            <Property aspects="device" datatype="xs:boolean" defaultAspect="device" name="j2me_motorola_lwt"/>
            <Property aspects="device" datatype="xs:boolean" defaultAspect="device" name="doja_3_5"/>
            <Property aspects="device" datatype="xs:boolean" defaultAspect="device" name="j2me_wbmp"/>
            <Property aspects="device" datatype="xs:boolean" defaultAspect="device" name="j2me_rmf"/>
            <Property aspects="device" datatype="xs:boolean" defaultAspect="device" name="j2me_wma"/>
            <Property aspects="device" datatype="xs:integer" defaultAspect="device" name="j2me_left_softkey_code"/>
            <Property aspects="device" datatype="xs:boolean" defaultAspect="device" name="j2me_jtwi"/>
            <Property aspects="device" datatype="xs:boolean" defaultAspect="device" name="j2me_jpg"/>
            <Property aspects="device" datatype="xs:integer" defaultAspect="device" name="j2me_return_key_code"/>
            <Property aspects="device" datatype="xs:boolean" defaultAspect="device" name="j2me_real8"/>
            <Property aspects="device" datatype="xs:integer" defaultAspect="device" name="j2me_max_record_store_size"/>
            <Property aspects="device" datatype="xs:boolean" defaultAspect="device" name="j2me_realmedia"/>
            <Property aspects="device" datatype="xs:boolean" defaultAspect="device" name="j2me_midp_1_0"/>
            <Property aspects="device" datatype="xs:boolean" defaultAspect="device" name="j2me_bmp3"/>
            <Property aspects="device" datatype="xs:boolean" defaultAspect="device" name="j2me_midi"/>
            <Property aspects="device" datatype="xs:boolean" defaultAspect="device" name="j2me_btapi"/>
            <Property aspects="device" datatype="xs:boolean" defaultAspect="device" name="j2me_locapi"/>
            <Property aspects="device" datatype="xs:boolean" defaultAspect="device" name="j2me_siemens_extension"/>
            <Property aspects="device" datatype="xs:boolean" defaultAspect="device" name="j2me_h263"/>
            <Property aspects="device" datatype="xs:boolean" defaultAspect="device" name="j2me_audio_capture_enabled"/>
            <Property aspects="device" datatype="xs:boolean" defaultAspect="device" name="j2me_midp_2_0"/>
            <Property aspects="device" datatype="xs:boolean" defaultAspect="device" name="j2me_datefield_no_accepts_null_date"/>
            <Property aspects="device" datatype="xs:boolean" defaultAspect="device" name="j2me_aac"/>
            <Property aspects="device" datatype="xs:string" defaultAspect="device" name="j2me_capture_image_formats"/>
            <Property aspects="device" datatype="xs:integer" defaultAspect="device" name="j2me_select_key_code"/>
            <Property aspects="device" datatype="xs:boolean" defaultAspect="device" name="j2me_xmf"/>
            <Property aspects="device" datatype="xs:boolean" defaultAspect="device" name="j2me_photo_capture_enabled"/>
            <Property aspects="device" datatype="xs:boolean" defaultAspect="device" name="j2me_realaudio"/>
            <Property aspects="device" datatype="xs:boolean" defaultAspect="device" name="j2me_realvideo"/>
            <Property aspects="device" datatype="xs:boolean" defaultAspect="device" name="j2me_mp3"/>
            <Property aspects="device" datatype="xs:boolean" defaultAspect="device" name="j2me_png"/>
            <Property aspects="device" datatype="xs:boolean" defaultAspect="device" name="j2me_au"/>
            <Property aspects="device" datatype="xs:integer" defaultAspect="device" name="j2me_screen_width"/>
            <Property aspects="device" datatype="xs:boolean" defaultAspect="device" name="j2me_mp4"/>
            <Property aspects="device" datatype="xs:boolean" defaultAspect="device" name="j2me_mmapi_1_0"/>
            <Property aspects="device" datatype="xs:boolean" defaultAspect="device" name="j2me_http"/>
            <Property aspects="device" datatype="xs:boolean" defaultAspect="device" name="j2me_imelody"/>
            <Property aspects="device" datatype="xs:boolean" defaultAspect="device" name="j2me_socket"/>
            <Property aspects="device" datatype="xs:boolean" defaultAspect="device" name="j2me_3dapi"/>
            <Property aspects="device" datatype="xs:integer" defaultAspect="device" name="j2me_bits_per_pixel"/>
            <Property aspects="device" datatype="xs:boolean" defaultAspect="device" name="j2me_mmapi_1_1"/>
            <Property aspects="device" datatype="xs:boolean" defaultAspect="device" name="j2me_udp"/>
            <Property aspects="device" datatype="xs:boolean" defaultAspect="device" name="j2me_wav"/>
            <Property aspects="device" datatype="xs:integer" defaultAspect="device" name="j2me_middle_softkey_code"/>
            <Property aspects="device" datatype="xs:boolean" defaultAspect="device" name="j2me_svgt"/>
            <Property aspects="device" datatype="xs:boolean" defaultAspect="device" name="j2me_gif"/>
            <Property aspects="device" datatype="xs:boolean" defaultAspect="device" name="j2me_siemens_color_game"/>
            <Property aspects="device" datatype="xs:integer" defaultAspect="device" name="j2me_max_jar_size"/>
            <Property aspects="device" datatype="xs:boolean" defaultAspect="device" name="j2me_wmapi_1_0"/>
            <Property aspects="device" datatype="xs:boolean" defaultAspect="device" name="j2me_nokia_ui"/>
            <Property aspects="device" datatype="xs:integer" defaultAspect="device" name="j2me_screen_height"/>
            <Property aspects="device" datatype="xs:boolean" defaultAspect="device" name="j2me_wmapi_1_1"/>
            <Property aspects="device" datatype="xs:boolean" defaultAspect="device" name="j2me_wmapi_2_0"/>
            <Property aspects="device" datatype="xs:boolean" defaultAspect="device" name="doja_1_0"/>
            <Property aspects="device" datatype="xs:boolean" defaultAspect="device" name="j2me_serial"/>
            <Property aspects="device" datatype="xs:boolean" defaultAspect="device" name="doja_2_0"/>
            <Property aspects="device" datatype="xs:boolean" defaultAspect="device" name="j2me_bmp"/>
            <Property aspects="device" datatype="xs:boolean" defaultAspect="device" name="j2me_amr"/>
            <Property aspects="device" datatype="xs:boolean" defaultAspect="device" name="j2me_gif89a"/>
            <Property aspects="device" datatype="xs:boolean" defaultAspect="device" name="j2me_cldc_1_0"/>
            <Property aspects="device" datatype="xs:boolean" defaultAspect="device" name="doja_2_1"/>
            <Property aspects="device" datatype="xs:boolean" defaultAspect="device" name="doja_3_0"/>
            <Property aspects="device" datatype="xs:boolean" defaultAspect="device" name="j2me_cldc_1_1"/>
            <Property aspects="device" datatype="xs:boolean" defaultAspect="device" name="doja_2_2"/>
            <Property aspects="device" datatype="xs:boolean" defaultAspect="device" name="doja_4_0"/>
            <Property aspects="device" datatype="xs:boolean" defaultAspect="device" name="j2me_3gpp"/>
            <Property aspects="device" datatype="xs:boolean" defaultAspect="device" name="j2me_video_capture_enabled"/>
            <Property aspects="device" datatype="xs:integer" defaultAspect="device" name="j2me_canvas_height"/>
            <Property aspects="device" datatype="xs:boolean" defaultAspect="device" name="j2me_https"/>
            <Property aspects="device" datatype="xs:boolean" defaultAspect="device" name="j2me_mpeg4"/>
            <Property aspects="device" datatype="xs:integer" defaultAspect="device" name="j2me_storage_size"/>
            <Property aspects="device" datatype="xs:boolean" defaultAspect="device" name="mms_3gpp"/>
            <Property aspects="device" datatype="xs:boolean" defaultAspect="device" name="mms_wbxml"/>
            <Property aspects="device" datatype="xs:boolean" defaultAspect="device" name="mms_symbian_install"/>
            <Property aspects="device" datatype="xs:boolean" defaultAspect="device" name="mms_png"/>
            <Property aspects="device" datatype="xs:integer" defaultAspect="device" name="mms_max_size"/>
            <Property aspects="device" datatype="xs:boolean" defaultAspect="device" name="mms_rmf"/>
            <Property aspects="device" datatype="xs:boolean" defaultAspect="device" name="mms_nokia_operatorlogo"/>
            <Property aspects="device" datatype="xs:integer" defaultAspect="device" name="mms_max_width"/>
            <Property aspects="device" datatype="xs:integer" defaultAspect="device" name="mms_max_frame_rate"/>
            <Property aspects="device" datatype="xs:boolean" defaultAspect="device" name="mms_wml"/>
            <Property aspects="device" datatype="xs:boolean" defaultAspect="device" name="mms_evrc"/>
            <Property aspects="device" datatype="xs:boolean" defaultAspect="device" name="mms_spmidi"/>
            <Property aspects="device" datatype="xs:boolean" defaultAspect="device" name="mms_gif_static"/>
            <Property aspects="device" datatype="xs:integer" defaultAspect="device" name="mms_max_height"/>
            <Property aspects="device" datatype="xs:boolean" defaultAspect="device" name="sender"/>
            <Property aspects="device" datatype="xs:boolean" defaultAspect="device" name="mms_video"/>
            <Property aspects="device" datatype="xs:boolean" defaultAspect="device" name="mms_vcard"/>
            <Property aspects="device" datatype="xs:boolean" defaultAspect="device" name="mms_nokia_3dscreensaver"/>
            <Property aspects="device" datatype="xs:boolean" defaultAspect="device" name="mms_qcelp"/>
            <Property aspects="device" datatype="xs:boolean" defaultAspect="device" name="mms_midi_polyphonic"/>
            <Property aspects="device" datatype="xs:boolean" defaultAspect="device" name="mms_wav"/>
            <Property aspects="device" datatype="xs:boolean" defaultAspect="device" name="mms_jpeg_progressive"/>
            <Property aspects="device" datatype="xs:boolean" defaultAspect="device" name="mms_jad"/>
            <Property aspects="device" datatype="xs:boolean" defaultAspect="device" name="mms_nokia_ringingtone"/>
            <Property aspects="device" datatype="xs:boolean" defaultAspect="device" name="built_in_recorder"/>
            <Property aspects="device" datatype="xs:boolean" defaultAspect="device" name="mms_midi_monophonic"/>
            <Property aspects="device" datatype="xs:boolean" defaultAspect="device" name="mms_3gpp2"/>
            <Property aspects="device" datatype="xs:boolean" defaultAspect="device" name="mms_wmlc"/>
            <Property aspects="device" datatype="xs:boolean" defaultAspect="device" name="mms_nokia_wallpaper"/>
            <Property aspects="device" datatype="xs:boolean" defaultAspect="device" name="mms_bmp"/>
            <Property aspects="device" datatype="xs:boolean" defaultAspect="device" name="mms_vcalendar"/>
            <Property aspects="device" datatype="xs:boolean" defaultAspect="device" name="mms_jar"/>
            <Property aspects="device" datatype="xs:boolean" defaultAspect="device" name="mms_ota_bitmap"/>
            <Property aspects="device" datatype="xs:boolean" defaultAspect="device" name="mms_mp3"/>
            <Property aspects="device" datatype="xs:boolean" defaultAspect="device" name="mms_mmf"/>
            <Property aspects="device" datatype="xs:boolean" defaultAspect="device" name="mms_amr"/>
            <Property aspects="device" datatype="xs:boolean" defaultAspect="device" name="mms_wbmp"/>
            <Property aspects="device" datatype="xs:boolean" defaultAspect="device" name="built_in_camera"/>
            <Property aspects="device" datatype="xs:boolean" defaultAspect="device" name="receiver"/>
            <Property aspects="device" datatype="xs:boolean" defaultAspect="device" name="mms_mp4"/>
            <Property aspects="device" datatype="xs:boolean" defaultAspect="device" name="mms_xmf"/>
            <Property aspects="device" datatype="xs:boolean" defaultAspect="device" name="mms_jpeg_baseline"/>
            <Property aspects="device" datatype="xs:integer" defaultAspect="device" name="mms_midi_polyphonic_voices"/>
            <Property aspects="device" datatype="xs:boolean" defaultAspect="device" name="mms_gif_animated"/>
            <Property aspects="device" datatype="xs:boolean" defaultAspect="device" name="ems"/>
            <Property aspects="device" datatype="xs:boolean" defaultAspect="device" name="text_imelody"/>
            <Property aspects="device" datatype="xs:boolean" defaultAspect="device" name="nokiaring"/>
            <Property aspects="device" datatype="xs:string" defaultAspect="device" name="siemens_logo_height"/>
            <Property aspects="device" datatype="xs:boolean" defaultAspect="device" name="ems_variablesizedpictures"/>
            <Property aspects="device" datatype="xs:boolean" defaultAspect="device" name="sckl_groupgraphic"/>
            <Property aspects="device" datatype="xs:boolean" defaultAspect="device" name="siemens_ota"/>
            <Property aspects="device" datatype="xs:boolean" defaultAspect="device" name="sagem_v1"/>
            <Property aspects="device" datatype="xs:boolean" defaultAspect="device" name="largeoperatorlogo"/>
            <Property aspects="device" datatype="xs:boolean" defaultAspect="device" name="sagem_v2"/>
            <Property aspects="device" datatype="xs:integer" defaultAspect="device" name="ems_version"/>
            <Property aspects="device" datatype="xs:boolean" defaultAspect="device" name="ems_odi"/>
            <Property aspects="device" datatype="xs:boolean" defaultAspect="device" name="nokiavcal"/>
            <Property aspects="device" datatype="xs:boolean" defaultAspect="device" name="operatorlogo"/>
            <Property aspects="device" datatype="xs:string" defaultAspect="device" name="siemens_logo_width"/>
            <Property aspects="device" datatype="xs:boolean" defaultAspect="device" name="ems_imelody"/>
            <Property aspects="device" datatype="xs:boolean" defaultAspect="device" name="sckl_vcard"/>
            <Property aspects="device" datatype="xs:string" defaultAspect="device" name="siemens_screensaver_width"/>
            <Property aspects="device" datatype="xs:boolean" defaultAspect="device" name="sckl_operatorlogo"/>
            <Property aspects="device" datatype="xs:boolean" defaultAspect="device" name="panasonic"/>
            <Property aspects="device" datatype="xs:boolean" defaultAspect="device" name="ems_upi"/>
            <Property aspects="device" datatype="xs:boolean" defaultAspect="device" name="nokiavcard"/>
            <Property aspects="device" datatype="xs:boolean" defaultAspect="device" name="callericon"/>
            <Property aspects="device" datatype="xs:boolean" defaultAspect="device" name="sms_enabled"/>
            <Property aspects="device" datatype="xs:boolean" defaultAspect="device" name="gprtf"/>
            <Property aspects="device" datatype="xs:string" defaultAspect="device" name="siemens_screensaver_height"/>
            <Property aspects="device" datatype="xs:boolean" defaultAspect="device" name="sckl_ringtone"/>
            <Property aspects="device" datatype="xs:boolean" defaultAspect="device" name="picturemessage"/>
            <Property aspects="device" datatype="xs:boolean" defaultAspect="device" name="sckl_vcalendar"/>
            <Property aspects="device" datatype="xs:boolean" defaultAspect="device" name="rmf"/>
            <Property aspects="device" datatype="xs:boolean" defaultAspect="device" name="qcelp"/>
            <Property aspects="device" datatype="xs:boolean" defaultAspect="device" name="awb"/>
            <Property aspects="device" datatype="xs:boolean" defaultAspect="device" name="smf"/>
            <Property aspects="device" datatype="xs:boolean" defaultAspect="device" name="wav"/>
            <Property aspects="device" datatype="xs:boolean" defaultAspect="device" name="nokia_ringtone"/>
            <Property aspects="device" datatype="xs:boolean" defaultAspect="device" name="aac"/>
            <Property aspects="device" datatype="xs:boolean" defaultAspect="device" name="digiplug"/>
            <Property aspects="device" datatype="xs:boolean" defaultAspect="device" name="sp_midi"/>
            <Property aspects="device" datatype="xs:boolean" defaultAspect="device" name="compactmidi"/>
            <Property aspects="device" datatype="xs:integer" defaultAspect="device" name="voices"/>
            <Property aspects="device" datatype="xs:boolean" defaultAspect="device" name="mp3"/>
            <Property aspects="device" datatype="xs:boolean" defaultAspect="device" name="mld"/>
            <Property aspects="device" datatype="xs:boolean" defaultAspect="device" name="evrc"/>
            <Property aspects="device" datatype="xs:boolean" defaultAspect="device" name="amr"/>
            <Property aspects="device" datatype="xs:boolean" defaultAspect="device" name="xmf"/>
            <Property aspects="device" datatype="xs:boolean" defaultAspect="device" name="mmf"/>
            <Property aspects="device" datatype="xs:boolean" defaultAspect="device" name="imelody"/>
            <Property aspects="device" datatype="xs:boolean" defaultAspect="device" name="midi_monophonic"/>
            <Property aspects="device" datatype="xs:boolean" defaultAspect="device" name="au"/>
            <Property aspects="device" datatype="xs:boolean" defaultAspect="device" name="midi_polyphonic"/>
            <Property aspects="device" datatype="xs:string" defaultAspect="device" name="flash_lite_version"/>
            <Property aspects="device" datatype="xs:boolean" defaultAspect="device" name="fl_wallpaper"/>
            <Property aspects="device" datatype="xs:boolean" defaultAspect="device" name="fl_browser"/>
            <Property aspects="device" datatype="xs:boolean" defaultAspect="device" name="fl_screensaver"/>
            <Property aspects="device" datatype="xs:boolean" defaultAspect="device" name="fl_standalone"/>
            <Property aspects="device" datatype="xs:boolean" defaultAspect="device" name="full_flash_support"/>
            <Property aspects="device" datatype="xs:boolean" defaultAspect="device" name="fl_sub_lcd"/>
            <Property aspects="device" datatype="xs:string" defaultAspect="device" name="css_gradient"/>
            <Property aspects="device" datatype="xs:string" defaultAspect="device" name="css_border_image"/>
            <Property aspects="device" datatype="xs:string" defaultAspect="device" name="css_rounded_corners"/>
            <Property aspects="device" datatype="xs:boolean" defaultAspect="device" name="css_spriting"/>
            <Property aspects="device" datatype="xs:boolean" defaultAspect="device" name="css_supports_width_as_percentage"/>
            <Property aspects="device" datatype="xs:boolean" defaultAspect="device" name="is_transcoder"/>
            <Property aspects="device" datatype="xs:string" defaultAspect="device" name="transcoder_ua_header"/>
            <Property aspects="device" datatype="xs:boolean" defaultAspect="device" name="rss_support"/>
            <Property aspects="device" datatype="xs:boolean" defaultAspect="device" name="pdf_support"/>
            <Property aspects="device" datatype="xs:integer" defaultAspect="device" name="playback_oma_size_limit"/>
            <Property aspects="device" datatype="xs:string" defaultAspect="device" name="playback_acodec_aac"/>
            <Property aspects="device" datatype="xs:string" defaultAspect="device" name="playback_vcodec_h263_3"/>
            <Property aspects="device" datatype="xs:string" defaultAspect="device" name="playback_vcodec_mpeg4_asp"/>
            <Property aspects="device" datatype="xs:boolean" defaultAspect="device" name="playback_mp4"/>
            <Property aspects="device" datatype="xs:boolean" defaultAspect="device" name="playback_3gpp"/>
            <Property aspects="device" datatype="xs:integer" defaultAspect="device" name="playback_df_size_limit"/>
            <Property aspects="device" datatype="xs:string" defaultAspect="device" name="playback_acodec_amr"/>
            <Property aspects="device" datatype="xs:boolean" defaultAspect="device" name="playback_mov"/>
            <Property aspects="device" datatype="xs:string" defaultAspect="device" name="playback_wmv"/>
            <Property aspects="device" datatype="xs:boolean" defaultAspect="device" name="playback_acodec_qcelp"/>
            <Property aspects="device" datatype="xs:boolean" defaultAspect="device" name="progressive_download"/>
            <Property aspects="device" datatype="xs:integer" defaultAspect="device" name="playback_directdownload_size_limit"/>
            <Property aspects="device" datatype="xs:string" defaultAspect="device" name="playback_real_media"/>
            <Property aspects="device" datatype="xs:boolean" defaultAspect="device" name="playback_3g2"/>
            <Property aspects="device" datatype="xs:string" defaultAspect="device" name="playback_vcodec_mpeg4_sp"/>
            <Property aspects="device" datatype="xs:string" defaultAspect="device" name="playback_vcodec_h263_0"/>
            <Property aspects="device" datatype="xs:integer" defaultAspect="device" name="playback_inline_size_limit"/>
            <Property aspects="device" datatype="xs:boolean" defaultAspect="device" name="hinted_progressive_download"/>
            <Property aspects="device" datatype="xs:string" defaultAspect="device" name="playback_vcodec_h264_bp"/>
            <Property aspects="device" datatype="xs:string" defaultAspect="device" name="canvas_support"/>
            <Property aspects="device" datatype="xs:string" defaultAspect="device" name="viewport_width"/>
            <Property aspects="device" datatype="xs:string" defaultAspect="device" name="html_preferred_dtd"/>
            <Property aspects="device" datatype="xs:boolean" defaultAspect="device" name="viewport_supported"/>
            <Property aspects="device" datatype="xs:string" defaultAspect="device" name="viewport_minimum_scale"/>
            <Property aspects="device" datatype="xs:string" defaultAspect="device" name="viewport_initial_scale"/>
            <Property aspects="device" datatype="xs:boolean" defaultAspect="device" name="mobileoptimized"/>
            <Property aspects="device" datatype="xs:string" defaultAspect="device" name="viewport_maximum_scale"/>
            <Property aspects="device" datatype="xs:string" defaultAspect="device" name="viewport_userscalable"/>
            <Property aspects="device" datatype="xs:boolean" defaultAspect="device" name="image_inlining"/>
            <Property aspects="device" datatype="xs:boolean" defaultAspect="device" name="handheldfriendly"/>
            <Property aspects="device" datatype="xs:string" defaultAspect="device" name="from"/>
        </Properties>
    </VocabularyDescription>
</ODDR>
